{"numeroHistoriaClinica":"995761","apellidosPaciente":"GUANOTUNA UMAJINGA","nombresPaciente":"DAMIAN","sc":"0022104518","fechaExamen":"2024-02-02","horaExamen":"15:02:23","origen":"Consulta Externa","servicio":"CIRUGIA GENERAL","medico":"SERPA LARREA FRANS IVAN","motivo":"CAJA 4","ultimaValidacion":"","ultimoFiltrado":"2024-02-02 15:53:56","fechaEnvio":"","tipoValidacion":0,"validacionClinica":0,"validacionMicro":0,"procesoValidacion":0,"statusFiltro":1,"statusEnvio":0,"_PDF":"","_PCR":0,"_AC":0,"numEnvios":0,"enviosParciales":0,"validacionesParciales":[],"orderTests":[{"TestID":"6361"}],"dataClinica":[],"dataMicro":[],"reglasFiltrosEnvio":[{"id":"1","nombreFiltro":"ENVIAR SOLO CONSULTA EXTERNA","eNe":"1","tipoValidacion":"1","strValidacion":"1","xServicio":null,"xOrigen":"Consulta Externa","xMotivo":null,"xMedico":null,"xIdPrueba":null,"xQR":null,"envio":"{\"dirrecciones\": \"1\"}","statusFiltro":"1","timestampCreate":null,"userCreate":null,"statusEnvio":0}],"reglasFiltrosNoEnvio":[{"id":"291","nombreFiltro":"NO ENVIAR PRUEBA 6361","eNe":"0","tipoValidacion":"1","strValidacion":null,"xServicio":null,"xOrigen":null,"xMotivo":null,"xMedico":null,"xIdPrueba":"6361","xQR":null,"envio":null,"statusFiltro":"1","timestampCreate":null,"userCreate":null}],"formatoQR":[],"logsEnvio":[],"correosElectronicos":[]}