{"numeroHistoriaClinica":"18444","apellidosPaciente":"GUERRERO AGUILERA","nombresPaciente":"BLANCA MARIA","sc":"0022102141","fechaExamen":"2024-01-21","horaExamen":"18:03:16","origen":"Hospitalizaci\u00f3n","servicio":"INFECTOLOGIA","medico":"DAVALOS PEREZ ALVARO FELIPE","motivo":"CAJA 1","ultimaValidacion":"","ultimoFiltrado":"2024-01-21 20:05:52","fechaEnvio":"","tipoValidacion":0,"validacionClinica":0,"validacionMicro":0,"procesoValidacion":0,"statusFiltro":1,"statusEnvio":0,"_PDF":"","_PCR":0,"_AC":0,"numEnvios":0,"enviosParciales":0,"validacionesParciales":[],"orderTests":[{"TestID":"1250"},{"TestID":"1251"},{"TestID":"1252"},{"TestID":"1254"},{"TestID":"1255"},{"TestID":"1256"},{"TestID":"2680"}],"dataClinica":[],"dataMicro":[],"reglasFiltrosEnvio":[],"reglasFiltrosNoEnvio":[{"id":"6","nombreFiltro":"NO ENVIAR HOSPITALIZACION A PTE","eNe":"0","tipoValidacion":"1","strValidacion":null,"xServicio":null,"xOrigen":"Hospitalizaci\u00f3n","xMotivo":null,"xMedico":null,"xIdPrueba":null,"xQR":null,"envio":null,"statusFiltro":"1","timestampCreate":null,"userCreate":null}],"formatoQR":[],"logsEnvio":[],"correosElectronicos":[]}