{"numeroHistoriaClinica":"944471","apellidosPaciente":"VASCONEZ ALIAGA","nombresPaciente":"DOMINICK LIONEL","sc":"0022120569","fechaExamen":"2024-04-20","horaExamen":"22:32:48","origen":"Urgencias","servicio":"EMERGENCIA","medico":"MONTA??O PRADO LUIS FERNANDO","motivo":"METROLAB","ultimaValidacion":"","ultimoFiltrado":"2024-04-21 01:09:04","fechaEnvio":"","tipoValidacion":0,"validacionClinica":0,"validacionMicro":0,"procesoValidacion":0,"statusFiltro":1,"statusEnvio":0,"_PDF":"","_PCR":0,"_AC":0,"numEnvios":0,"enviosParciales":0,"validacionesParciales":[],"orderTests":[{"TestID":"3353"}],"dataClinica":[],"dataMicro":[],"reglasFiltrosEnvio":[],"reglasFiltrosNoEnvio":[{"id":"5","nombreFiltro":"NO ENVIAR URGENCIAS A PTE","eNe":"0","tipoValidacion":"1","strValidacion":null,"xServicio":null,"xOrigen":"Urgencias","xMotivo":null,"xMedico":null,"xIdPrueba":null,"xQR":null,"envio":null,"statusFiltro":"1","timestampCreate":null,"userCreate":null},{"id":"2","nombreFiltro":"NO ENVIAR METROLAB","eNe":"0","tipoValidacion":"1","strValidacion":null,"xServicio":null,"xOrigen":null,"xMotivo":"METROLAB","xMedico":"METROLAB METROLAB","xIdPrueba":null,"xQR":null,"envio":null,"statusFiltro":"1","timestampCreate":null,"userCreate":null}],"formatoQR":[],"logsEnvio":[],"correosElectronicos":[]}