{"numeroHistoriaClinica":"991","apellidosPaciente":"SEVILLA ARIAS","nombresPaciente":"MARCELO HERNAN","sc":"0022090991","fechaExamen":"2023-11-27","horaExamen":"07:17:03","origen":"Consulta Externa","servicio":"ENDOCRINOLOGIA","medico":"REYES POSSO MONICA XIMENA","motivo":"CAJA 4","ultimaValidacion":"2023-11-27 12:51:00","ultimoFiltrado":"2023-11-27 12:30:29","fechaEnvio":"2023-11-27 12:52:01","tipoValidacion":1,"validacionClinica":1,"validacionMicro":0,"procesoValidacion":1,"statusFiltro":1,"statusEnvio":4,"_PDF":"","_PCR":0,"_AC":11,"numEnvios":1,"enviosParciales":1,"validacionesParciales":{"Content":"http:\/\/172.16.2.221:9390\/Reports\/pdf\/preview_1_1020494.pdf"},"orderTests":[{"TestID":"2001"},{"TestID":"3004"},{"TestID":"3007"},{"TestID":"3036"},{"TestID":"3045"},{"TestID":"3094"}],"dataClinica":[{"TestID":"2001","TestStatus":"4","TestName":"Glucosa","ultimaValidacion":"2023-11-27 12:51:01"},{"TestID":"3004","TestStatus":"4","TestName":"FT4","ultimaValidacion":"2023-11-27 12:51:01"},{"TestID":"3007","TestStatus":"4","TestName":"TSH","ultimaValidacion":"2023-11-27 12:51:01"},{"TestID":"3036","TestStatus":"4","TestName":"Cortisol Am","ultimaValidacion":"2023-11-27 12:51:01"},{"TestID":"3045","TestStatus":"4","TestName":"Insulina Ayunas","ultimaValidacion":"2023-11-27 12:51:01"},{"TestID":"3094","TestStatus":"4","TestName":"Indice Homa","ultimaValidacion":"2023-11-27 12:51:01"}],"dataMicro":[],"reglasFiltrosEnvio":[{"id":"1","nombreFiltro":"ENVIAR SOLO CONSULTA EXTERNA","eNe":"1","tipoValidacion":"1","strValidacion":"1","xServicio":null,"xOrigen":"Consulta Externa","xMotivo":null,"xMedico":null,"xIdPrueba":null,"xQR":null,"envio":"{\"dirrecciones\": \"1\"}","statusFiltro":"1","timestampCreate":null,"userCreate":null,"statusEnvio":0}],"reglasFiltrosNoEnvio":[],"formatoQR":[],"logsEnvio":[{"correosPaciente":[{"To":"marcelosevilla1@gmail.com","SubmittedAt":"2023-11-27T17:52:01.7564397Z","MessageID":"8ae3e8b4-7322-431f-a713-c20678daa240","ErrorCode":0,"Message":"OK"}]},{"timestampLog":"2023-11-27 12:52:01","log":"Proceso de env\u00edo Exitoso"},{"timestampLog":"2023-11-27 12:52:01","log":"Envio exitoso de Notificaci\u00f3n."}],"correosElectronicos":[{"dirrecciones":"marcelosevilla1@gmail.com"}],"logValidacion":{"PreviewResult":"http:\/\/172.16.2.221:9390\/Reports\/pdf\/preview_1_1020494.pdf"},"corteEnvio":1}