{"numeroHistoriaClinica":"96977","apellidosPaciente":"ZURITA GARCIA","nombresPaciente":"SORAYA DEL ROSARIO","sc":"0022115209","fechaExamen":"2024-03-25","horaExamen":"11:28:50","origen":"Consulta Externa","servicio":"GASTROENTEROLOGIA","medico":"RODRIGUEZ SUAREZ JAVIER ESTE","motivo":"CAJA 4","ultimaValidacion":"2024-03-25 17:36:00","ultimoFiltrado":"2024-03-25 13:03:14","fechaEnvio":"2024-03-25 17:37:02","tipoValidacion":1,"validacionClinica":1,"validacionMicro":0,"procesoValidacion":1,"statusFiltro":1,"statusEnvio":4,"_PDF":"","_PCR":0,"_AC":2,"numEnvios":2,"enviosParciales":1,"validacionesParciales":{"Content":"http:\/\/172.16.2.221:9390\/Reports\/pdf\/preview_1_1050543.pdf"},"orderTests":[{"TestID":"1001"},{"TestID":"1023"},{"TestID":"1025"},{"TestID":"1027"},{"TestID":"1029"},{"TestID":"1031"},{"TestID":"1033"},{"TestID":"1035"},{"TestID":"1037"},{"TestID":"1039"},{"TestID":"1044"},{"TestID":"1070"},{"TestID":"1075"},{"TestID":"1078"},{"TestID":"2386"}],"dataClinica":[{"TestID":"1001","TestStatus":"4","TestName":"Leucocitos","ultimaValidacion":"2024-03-25 17:36:01"},{"TestID":"1023","TestStatus":"4","TestName":"Gl\u00f3bulos Rojos","ultimaValidacion":"2024-03-25 17:36:01"},{"TestID":"1025","TestStatus":"4","TestName":"Hemoglobina","ultimaValidacion":"2024-03-25 17:36:01"},{"TestID":"1027","TestStatus":"4","TestName":"Hematocrito","ultimaValidacion":"2024-03-25 17:36:01"},{"TestID":"1029","TestStatus":"4","TestName":"Volumen Corpuscular Medio","ultimaValidacion":"2024-03-25 17:36:01"},{"TestID":"1031","TestStatus":"4","TestName":"Hemoglobina Corpuscular Media","ultimaValidacion":"2024-03-25 17:36:01"},{"TestID":"1033","TestStatus":"4","TestName":"Concentraci\u00f3n Hb Corpuscular M","ultimaValidacion":"2024-03-25 17:36:01"},{"TestID":"1035","TestStatus":"4","TestName":"Ancho De Distribuci\u00f3n G R Sd","ultimaValidacion":"2024-03-25 17:36:01"},{"TestID":"1037","TestStatus":"4","TestName":"Ancho De Distribuci\u00f3n G R Cv","ultimaValidacion":"2024-03-25 17:36:01"},{"TestID":"1039","TestStatus":"4","TestName":"Plaquetas","ultimaValidacion":"2024-03-25 17:36:01"},{"TestID":"1044","TestStatus":"5","TestName":"Observaci\u00f3n Bh","ultimaValidacion":"2024-03-25 17:36:01"},{"TestID":"1070","TestStatus":"4","TestName":"Ferritina","ultimaValidacion":"2024-03-25 17:36:01"},{"TestID":"1075","TestStatus":"4","TestName":"Vitamina B12","ultimaValidacion":"2024-03-25 17:36:01"},{"TestID":"1078","TestStatus":"4","TestName":"Acido F\u00f3lico","ultimaValidacion":"2024-03-25 17:36:01"},{"TestID":"2386","TestStatus":"4","TestName":"HEMATOCRITO HEMOGLOBINA","ultimaValidacion":"2024-03-25 17:36:01"}],"dataMicro":[],"reglasFiltrosEnvio":[{"id":"1","nombreFiltro":"ENVIAR SOLO CONSULTA EXTERNA","eNe":"1","tipoValidacion":"1","strValidacion":"1","xServicio":null,"xOrigen":"Consulta Externa","xMotivo":null,"xMedico":null,"xIdPrueba":null,"xQR":null,"envio":"{\"dirrecciones\": \"1\"}","statusFiltro":"1","timestampCreate":null,"userCreate":null,"statusEnvio":0}],"reglasFiltrosNoEnvio":[],"formatoQR":[],"logsEnvio":[{"correosPaciente":[{"ErrorCode":0,"Message":"OK","MessageID":"80da0535-d17a-4aa2-828a-51f7484940ef","SubmittedAt":"2024-03-25T19:02:05.557675Z","To":"sora16zura@hotmail.com"}]},{"timestampLog":"2024-03-25 14:02:04","log":"Proceso de env\u00edo Exitoso"},{"timestampLog":"2024-03-25 14:02:04","log":"Reproceso por Revalidaci\u00f3n de resultado."},{"correosPaciente":[{"ErrorCode":0,"Message":"OK","MessageID":"fac3cbe9-332f-4b1d-a7ea-b80d138e4923","SubmittedAt":"2024-03-25T22:37:03.2962324Z","To":"sora16zura@hotmail.com"}]},{"timestampLog":"2024-03-25 17:37:02","log":"Proceso de env\u00edo Exitoso"},{"timestampLog":"2024-03-25 17:37:02","log":"Envio exitoso de Notificaci\u00f3n."}],"correosElectronicos":[{"dirrecciones":"sora16zura@hotmail.com"}],"logValidacion":{"PreviewResult":"http:\/\/172.16.2.221:9390\/Reports\/pdf\/preview_1_1050543.pdf"},"corteEnvio":1}