{"numeroHistoriaClinica":"825867","apellidosPaciente":"CARVAJAL ZAMBRANO","nombresPaciente":"ELIANA CAROLINA","sc":"0022103793","fechaExamen":"2024-01-30","horaExamen":"09:12:05","origen":"Consulta Externa","servicio":"UROLOGIA","medico":"SALAZAR POLANCO RICARDO WILSON","motivo":"CAJA 1","ultimaValidacion":"2024-02-02 10:11:52","ultimoFiltrado":"2024-01-30 12:57:03","fechaEnvio":"2024-02-02 10:12:52","tipoValidacion":1,"validacionClinica":0,"validacionMicro":1,"procesoValidacion":1,"statusFiltro":1,"statusEnvio":4,"_PDF":"","_PCR":0,"_AC":3,"numEnvios":1,"enviosParciales":0,"validacionesParciales":[],"orderTests":[{"TestID":"7001"}],"dataClinica":[],"dataMicro":[{"TestID":"7001","TestStatus":"4","TestName":"Urocultivo","ultimaValidacion":"2024-02-02 10:11:52"}],"reglasFiltrosEnvio":[{"id":"1","nombreFiltro":"ENVIAR SOLO CONSULTA EXTERNA","eNe":"1","tipoValidacion":"1","strValidacion":"1","xServicio":null,"xOrigen":"Consulta Externa","xMotivo":null,"xMedico":null,"xIdPrueba":null,"xQR":null,"envio":"{\"dirrecciones\": \"1\"}","statusFiltro":"1","timestampCreate":null,"userCreate":null,"statusEnvio":0}],"reglasFiltrosNoEnvio":[],"formatoQR":[],"logsEnvio":[{"correosPaciente":[{"ErrorCode":0,"Message":"OK","MessageID":"cdf05a5a-88bf-4d15-9f73-5596e6e388fe","SubmittedAt":"2024-02-02T15:13:01.4056965Z","To":"eliana358@hotmail.com"}]},{"timestampLog":"2024-02-02 10:12:52","log":"Proceso de env\u00edo Exitoso"},{"timestampLog":"2024-02-02 10:12:52","log":"Envio exitoso de Notificaci\u00f3n."}],"correosElectronicos":[{"dirrecciones":"eliana358@hotmail.com"}],"corteEnvio":1}