{"numeroHistoriaClinica":"73091201","apellidosPaciente":"QUIROLA ATTI","nombresPaciente":"DANIELA MONSERRAT","sc":"0020324190","fechaExamen":"2024-01-26","horaExamen":"12:18:17","origen":"STAT (UCI\/NEO)","servicio":"NEONATOLOGIA","medico":"BENALCAZAR ZURITA MANUEL EDUAR","motivo":"URGENCIAS","ultimaValidacion":"2024-01-26 15:32:51","ultimoFiltrado":"2024-01-26 15:30:08","fechaEnvio":"2024-01-26 15:33:54","tipoValidacion":1,"validacionClinica":0,"validacionMicro":1,"procesoValidacion":1,"statusFiltro":1,"statusEnvio":4,"_PDF":"","_PCR":0,"_AC":0,"numEnvios":1,"enviosParciales":1,"validacionesParciales":{"Content":"http:\/\/172.16.2.221:9390\/Reports\/pdf\/preview_1_1035785.pdf"},"orderTests":[{"TestID":"7090"},{"TestID":"7210"}],"dataClinica":[],"dataMicro":[{"TestID":"7090","TestStatus":"4","TestName":"Clostridium Dificile Toxina A+B ","ultimaValidacion":"2024-01-26 15:32:53"},{"TestID":"7210","TestStatus":"5","TestName":"No. de Cultivo","ultimaValidacion":"2024-01-26 15:32:53"}],"reglasFiltrosEnvio":[{"id":"60","nombreFiltro":"ENVIAR PRUEBA 7090","eNe":"1","tipoValidacion":"1","strValidacion":"2","xServicio":null,"xOrigen":null,"xMotivo":null,"xMedico":null,"xIdPrueba":"7090","xQR":null,"envio":"{\"dirrecciones\": \"1\"}","statusFiltro":"1","timestampCreate":null,"userCreate":null,"statusEnvio":0}],"reglasFiltrosNoEnvio":[],"formatoQR":[],"logsEnvio":[{"correosPaciente":[{"ErrorCode":0,"Message":"OK","MessageID":"18568df3-805f-4926-8d0f-7b0aef1fbe13","SubmittedAt":"2024-01-26T20:34:03.9053401Z","To":"diego.quirola@tetrapak.com"},{"ErrorCode":0,"Message":"OK","MessageID":"3d68f080-45c4-4dfd-b183-eff9d55dcddf","SubmittedAt":"2024-01-26T20:34:04.4585512Z","To":"carla.atti87@hotmail.com"}]},{"timestampLog":"2024-01-26 15:33:54","log":"Proceso de env\u00edo Exitoso"},{"timestampLog":"2024-01-26 15:33:54","log":"Envio exitoso de Notificaci\u00f3n."}],"correosElectronicos":[{"dirrecciones":"diego.quirola@tetrapak.com"},{"dirrecciones":"carla.atti87@hotmail.com"}],"logValidacion":{"PreviewResult":"http:\/\/172.16.2.221:9390\/Reports\/pdf\/preview_1_1035785.pdf"},"corteEnvio":1}