{"numeroHistoriaClinica":"186452","apellidosPaciente":"REZABALA DELGADO","nombresPaciente":"MATILDE TEODORA","sc":"0022108762","fechaExamen":"2024-02-24","horaExamen":"08:01:07","origen":"Consulta Externa","servicio":"MEDICINA INTERNA","medico":"NIETO RAMOS CARLOS JAVIER","motivo":"CAJA 1","ultimaValidacion":"2024-02-24 12:41:41","ultimoFiltrado":"2024-02-24 12:23:58","fechaEnvio":"2024-02-24 14:00:45","tipoValidacion":1,"validacionClinica":1,"validacionMicro":0,"procesoValidacion":1,"statusFiltro":1,"statusEnvio":4,"_PDF":"","_PCR":0,"_AC":2,"numEnvios":1,"enviosParciales":0,"validacionesParciales":[],"orderTests":[{"TestID":"5045"}],"dataClinica":[{"TestID":"5045","TestStatus":"4","TestName":"Helycobacter Pylori En Heces","ultimaValidacion":"2024-02-24 12:41:42"}],"dataMicro":[],"reglasFiltrosEnvio":[{"id":"1","nombreFiltro":"ENVIAR SOLO CONSULTA EXTERNA","eNe":"1","tipoValidacion":"1","strValidacion":"1","xServicio":null,"xOrigen":"Consulta Externa","xMotivo":null,"xMedico":null,"xIdPrueba":null,"xQR":null,"envio":"{\"dirrecciones\": \"1\"}","statusFiltro":"1","timestampCreate":null,"userCreate":null,"statusEnvio":0}],"reglasFiltrosNoEnvio":[],"formatoQR":[],"logsEnvio":[{"correosPaciente":[{"ErrorCode":0,"Message":"OK","MessageID":"3ef6e02a-4f68-4fe3-b848-d1d52f72341c","SubmittedAt":"2024-02-24T19:01:05.369359Z","To":"matilderezabala1959@gmail.com"}]},{"timestampLog":"2024-02-24 14:00:45","log":"Proceso de env\u00edo Exitoso"},{"timestampLog":"2024-02-24 14:00:45","log":"Envio exitoso de Notificaci\u00f3n."}],"correosElectronicos":[{"dirrecciones":"matilderezabala1959@gmail.com"}],"corteEnvio":2}