{"numeroHistoriaClinica":"997240","apellidosPaciente":"FIERRO ROOT","nombresPaciente":"JENNA MORGAN","sc":"0022118464","fechaExamen":"2024-04-10","horaExamen":"14:52:07","origen":"Consulta Externa","servicio":"GASTROENTEROLOGIA","medico":"ZAMBRANO GODOY JUAN JOSE","motivo":"CAJA 4","ultimaValidacion":"2024-04-10 21:35:55","ultimoFiltrado":"2024-04-10 16:06:13","fechaEnvio":"2024-04-10 21:35:56","tipoValidacion":1,"validacionClinica":1,"validacionMicro":1,"procesoValidacion":1,"statusFiltro":1,"statusEnvio":4,"_PDF":"","_PCR":0,"_AC":5,"numEnvios":2,"enviosParciales":1,"validacionesParciales":{"Content":"http:\/\/172.16.2.221:9390\/Reports\/pdf\/preview_1_1054640.pdf"},"orderTests":[{"TestID":"1062"},{"TestID":"1063"},{"TestID":"1068"},{"TestID":"1070"},{"TestID":"1073"},{"TestID":"4000"},{"TestID":"7200"}],"dataClinica":[{"TestID":"1062","TestStatus":"4","TestName":"Hierro S\u00e9rico","ultimaValidacion":"2024-04-10 21:35:55"},{"TestID":"1063","TestStatus":"4","TestName":"Transferrina","ultimaValidacion":"2024-04-10 21:35:55"},{"TestID":"1068","TestStatus":"4","TestName":"Ind. Saturaci\u00f3n Transferrina","ultimaValidacion":"2024-04-10 21:35:55"},{"TestID":"1070","TestStatus":"4","TestName":"Ferritina","ultimaValidacion":"2024-04-10 21:35:55"},{"TestID":"1073","TestStatus":"4","TestName":"Comentario","ultimaValidacion":"2024-04-10 21:35:55"},{"TestID":"4000","TestStatus":"4","TestName":"Amerita Cultivo De Orina","ultimaValidacion":"2024-04-10 21:35:55"}],"dataMicro":[{"TestID":"7200","TestStatus":"5","TestName":"Cultivo de orina S\/N amerita","ultimaValidacion":"2024-04-10 21:35:55"}],"reglasFiltrosEnvio":[{"id":"1","nombreFiltro":"ENVIAR SOLO CONSULTA EXTERNA","eNe":"1","tipoValidacion":"1","strValidacion":"1","xServicio":null,"xOrigen":"Consulta Externa","xMotivo":null,"xMedico":null,"xIdPrueba":null,"xQR":null,"envio":"{\"dirrecciones\": \"1\"}","statusFiltro":"1","timestampCreate":null,"userCreate":null,"statusEnvio":0}],"reglasFiltrosNoEnvio":[],"formatoQR":[],"logsEnvio":[{"correosPaciente":[{"ErrorCode":0,"Message":"OK","MessageID":"12fa8fc1-4de0-40e0-926a-09a869ce4179","SubmittedAt":"2024-04-10T22:01:03.2821532Z","To":"jfierro2013@gmail.com"}]},{"timestampLog":"2024-04-10 17:00:57","log":"Proceso de env\u00edo Exitoso"},{"timestampLog":"2024-04-10 17:00:57","log":"Reproceso por Revalidaci\u00f3n de resultado."},{"correosPaciente":[{"ErrorCode":0,"Message":"OK","MessageID":"f5982907-2d50-4d7e-b24d-fb7af192524d","SubmittedAt":"2024-04-11T02:36:02.286638Z","To":"jfierro2013@gmail.com"}]},{"timestampLog":"2024-04-10 21:35:56","log":"Proceso de env\u00edo Exitoso"},{"timestampLog":"2024-04-10 21:35:56","log":"Envio exitoso de Notificaci\u00f3n."}],"correosElectronicos":[{"dirrecciones":"jfierro2013@gmail.com"}],"logValidacion":{"PreviewResult":"http:\/\/172.16.2.221:9390\/Reports\/pdf\/preview_1_1054640.pdf"},"corteEnvio":1}