{"numeroHistoriaClinica":"48811","apellidosPaciente":"VITERI BRAVO","nombresPaciente":"NORMA HIPATIA DE LOURDES","sc":"0022099854","fechaExamen":"2024-01-10","horaExamen":"09:09:42","origen":"Consulta Externa","servicio":"HEMATOLOGIA","medico":"ROJAS NOBOA JOHANNA CAROLINA","motivo":"CAJA 2","ultimaValidacion":"2024-01-10 14:02:41","ultimoFiltrado":"2024-01-10 12:29:58","fechaEnvio":"2024-01-10 14:03:42","tipoValidacion":1,"validacionClinica":1,"validacionMicro":0,"procesoValidacion":1,"statusFiltro":1,"statusEnvio":4,"_PDF":"","_PCR":0,"_AC":2,"numEnvios":1,"enviosParciales":0,"validacionesParciales":[],"orderTests":[{"TestID":"3620"}],"dataClinica":[{"TestID":"3620","TestStatus":"4","TestName":"Eritropoyetina (EPO)","ultimaValidacion":"2024-01-10 14:02:42"}],"dataMicro":[],"reglasFiltrosEnvio":[{"id":"1","nombreFiltro":"ENVIAR SOLO CONSULTA EXTERNA","eNe":"1","tipoValidacion":"1","strValidacion":"1","xServicio":null,"xOrigen":"Consulta Externa","xMotivo":null,"xMedico":null,"xIdPrueba":null,"xQR":null,"envio":"{\"dirrecciones\": \"1\"}","statusFiltro":"1","timestampCreate":null,"userCreate":null,"statusEnvio":0}],"reglasFiltrosNoEnvio":[],"formatoQR":[],"logsEnvio":[{"correosPaciente":[{"ErrorCode":0,"Message":"OK","MessageID":"c1ad339c-ca8f-4ab5-beb9-80eb5f38f618","SubmittedAt":"2024-01-10T19:04:00.3950854Z","To":"geoparedes1958@gmail.com"},{"ErrorCode":0,"Message":"OK","MessageID":"0e2ed5da-19c6-4f88-8d32-d5754d92b847","SubmittedAt":"2024-01-10T19:04:01.0112648Z","To":"NORMAVITERIBRAVO@GMAIL.COM"}]},{"timestampLog":"2024-01-10 14:03:42","log":"Proceso de env\u00edo Exitoso"},{"timestampLog":"2024-01-10 14:03:42","log":"Envio exitoso de Notificaci\u00f3n."}],"correosElectronicos":[{"dirrecciones":"geoparedes1958@gmail.com"},{"dirrecciones":"NORMAVITERIBRAVO@GMAIL.COM"}],"corteEnvio":2}