{"numeroHistoriaClinica":"456247","apellidosPaciente":"PINEIROS IRIGOYEN","nombresPaciente":"ANA CAROLINA","sc":"0022121698","fechaExamen":"2024-04-26","horaExamen":"09:34:28","origen":"Consulta Externa","servicio":"MEDICINA INTERNA","medico":"","motivo":"CAJA 3","ultimaValidacion":"2024-04-26 13:20:59","ultimoFiltrado":"2024-04-26 12:51:17","fechaEnvio":"2024-04-26 14:01:03","tipoValidacion":1,"validacionClinica":1,"validacionMicro":0,"procesoValidacion":1,"statusFiltro":1,"statusEnvio":4,"_PDF":"","_PCR":0,"_AC":2,"numEnvios":1,"enviosParciales":0,"validacionesParciales":[],"orderTests":[{"TestID":"1075"}],"dataClinica":[{"TestID":"1075","TestStatus":"4","TestName":"Vitamina B12","ultimaValidacion":"2024-04-26 13:21:00"}],"dataMicro":[],"reglasFiltrosEnvio":[{"id":"1","nombreFiltro":"ENVIAR SOLO CONSULTA EXTERNA","eNe":"1","tipoValidacion":"1","strValidacion":"1","xServicio":null,"xOrigen":"Consulta Externa","xMotivo":null,"xMedico":null,"xIdPrueba":null,"xQR":null,"envio":"{\"dirrecciones\": \"1\"}","statusFiltro":"1","timestampCreate":null,"userCreate":null,"statusEnvio":0}],"reglasFiltrosNoEnvio":[],"formatoQR":[],"logsEnvio":[{"correosPaciente":[{"ErrorCode":0,"Message":"OK","MessageID":"a2d4ca42-e3b7-4e75-9927-581edd90f566","SubmittedAt":"2024-04-26T19:01:05.1485169Z","To":"caritoirigoyen@hotmail.com"}]},{"timestampLog":"2024-04-26 14:01:03","log":"Proceso de env\u00edo Exitoso"},{"timestampLog":"2024-04-26 14:01:03","log":"Envio exitoso de Notificaci\u00f3n."}],"correosElectronicos":[{"dirrecciones":"caritoirigoyen@hotmail.com"}],"corteEnvio":2}