{"numeroHistoriaClinica":"954052","apellidosPaciente":"ZAMBONINO ROBAYO","nombresPaciente":"CECILIA DEL CARMEN","sc":"0022096527","fechaExamen":"2023-12-22","horaExamen":"07:16:33","origen":"Consulta Externa","servicio":"MEDICINA INTERNA","medico":"","motivo":"CAJA 1","ultimaValidacion":"2023-12-22 12:44:21","ultimoFiltrado":"2023-12-22 12:20:36","fechaEnvio":"2023-12-22 12:45:23","tipoValidacion":1,"validacionClinica":1,"validacionMicro":0,"procesoValidacion":1,"statusFiltro":1,"statusEnvio":4,"_PDF":"","_PCR":0,"_AC":11,"numEnvios":1,"enviosParciales":1,"validacionesParciales":{"Content":"http:\/\/172.16.2.221:9390\/Reports\/pdf\/preview_1_1027308.pdf"},"orderTests":[{"TestID":"7730"},{"TestID":"7731"},{"TestID":"7733"},{"TestID":"7741"},{"TestID":"7742"},{"TestID":"7743"},{"TestID":"7744"},{"TestID":"7745"},{"TestID":"7746"},{"TestID":"7748"}],"dataClinica":[{"TestID":"7730","TestStatus":"4","TestName":"Exhalaci\u00f3n De Hidrogeno 3H","ultimaValidacion":"2023-12-22 12:44:23"},{"TestID":"7731","TestStatus":"4","TestName":"Exhalaci\u00f3n De Hidr\u00f3geno Basal","ultimaValidacion":"2023-12-22 12:44:23"},{"TestID":"7733","TestStatus":"4","TestName":"Sintomas","ultimaValidacion":"2023-12-22 12:44:23"},{"TestID":"7741","TestStatus":"4","TestName":"LACTULOSA SOBRECRECIMIENTO BACTERIANO","ultimaValidacion":"2023-12-22 12:44:23"},{"TestID":"7742","TestStatus":"5","TestName":"Dosis \/Kg-Peso","ultimaValidacion":"2023-12-22 12:44:23"},{"TestID":"7743","TestStatus":"4","TestName":"Dosis Administrada","ultimaValidacion":"2023-12-22 12:44:23"},{"TestID":"7744","TestStatus":"4","TestName":"Exhalaci\u00f3n De Hidrogeno 1.5 H","ultimaValidacion":"2023-12-22 12:44:23"},{"TestID":"7745","TestStatus":"4","TestName":"Exhalaci\u00f3n De Hidrogeno 1H","ultimaValidacion":"2023-12-22 12:44:23"},{"TestID":"7746","TestStatus":"4","TestName":"Exhalaci\u00f3n De Hidrogeno 2.5 H","ultimaValidacion":"2023-12-22 12:44:23"},{"TestID":"7748","TestStatus":"4","TestName":"Exhalaci\u00f3n De Hidrogeno 2H","ultimaValidacion":"2023-12-22 12:44:23"}],"dataMicro":[],"reglasFiltrosEnvio":[{"id":"1","nombreFiltro":"ENVIAR SOLO CONSULTA EXTERNA","eNe":"1","tipoValidacion":"1","strValidacion":"1","xServicio":null,"xOrigen":"Consulta Externa","xMotivo":null,"xMedico":null,"xIdPrueba":null,"xQR":null,"envio":"{\"dirrecciones\": \"1\"}","statusFiltro":"1","timestampCreate":null,"userCreate":null,"statusEnvio":0}],"reglasFiltrosNoEnvio":[],"formatoQR":[],"logsEnvio":[{"correosPaciente":[{"ErrorCode":0,"Message":"OK","MessageID":"030e215e-32fd-48f4-af84-9a6320d756b5","SubmittedAt":"2023-12-22T17:46:02.5795783Z","To":"metrolab@hmetro.med.ec"}]},{"timestampLog":"2023-12-22 12:45:23","log":"Proceso de env\u00edo Exitoso"},{"timestampLog":"2023-12-22 12:45:23","log":"Envio exitoso de Notificaci\u00f3n."}],"correosElectronicos":[{"dirrecciones":"metrolab@hmetro.med.ec"}],"logValidacion":{"PreviewResult":"http:\/\/172.16.2.221:9390\/Reports\/pdf\/preview_1_1027308.pdf"},"corteEnvio":1}