{"numeroHistoriaClinica":"858319","apellidosPaciente":"CABRERA ANDRAMUNO","nombresPaciente":"ANDRES RENE","sc":"0022093673","fechaExamen":"2023-12-09","horaExamen":"03:17:01","origen":"Urgencias","servicio":"NEUROLOGIA","medico":"CASTRO UQUILLAS EDUARDO","motivo":"METROLAB","ultimaValidacion":"","ultimoFiltrado":"","fechaEnvio":"","tipoValidacion":0,"validacionClinica":0,"validacionMicro":0,"procesoValidacion":0,"statusFiltro":0,"statusEnvio":0,"_PDF":"","_PCR":0,"_AC":0,"numEnvios":0,"enviosParciales":0,"validacionesParciales":[],"orderTests":[],"dataClinica":[],"dataMicro":[],"reglasFiltrosEnvio":[],"reglasFiltrosNoEnvio":[],"formatoQR":[],"logsEnvio":[],"correosElectronicos":[]}