{"numeroHistoriaClinica":"77721","apellidosPaciente":"ALVEAR PEREZ","nombresPaciente":"ANA EULALIA MARCIA","sc":"0022121159","fechaExamen":"2024-04-24","horaExamen":"04:43:28","origen":"Hospitalizaci\u00f3n","servicio":"NEUROLOGIA","medico":"GOMEZ GUERRERO CONSTANZA MAG","motivo":"METROLAB","ultimaValidacion":"","ultimoFiltrado":"","fechaEnvio":"","tipoValidacion":0,"validacionClinica":0,"validacionMicro":0,"procesoValidacion":0,"statusFiltro":0,"statusEnvio":0,"_PDF":"","_PCR":0,"_AC":0,"numEnvios":0,"enviosParciales":0,"validacionesParciales":[],"orderTests":[],"dataClinica":[],"dataMicro":[],"reglasFiltrosEnvio":[],"reglasFiltrosNoEnvio":[],"formatoQR":[],"logsEnvio":[],"correosElectronicos":[]}