{"numeroHistoriaClinica":"31921501","apellidosPaciente":"RICAURTE BURGOS","nombresPaciente":"MARIA DE LOS ANGELES","sc":"0020257768","fechaExamen":"2024-01-03","horaExamen":"08:24:29","origen":"Consulta Externa","servicio":"IMAGEN","medico":"CORNEJO ALMEIDA DIEGO FRANCI","motivo":"","ultimaValidacion":"","ultimoFiltrado":"","fechaEnvio":"","tipoValidacion":0,"validacionClinica":0,"validacionMicro":0,"procesoValidacion":0,"statusFiltro":0,"statusEnvio":0,"_PDF":"","_PCR":0,"_AC":0,"numEnvios":0,"enviosParciales":0,"validacionesParciales":[],"orderTests":[],"dataClinica":[],"dataMicro":[],"reglasFiltrosEnvio":[],"reglasFiltrosNoEnvio":[],"formatoQR":[],"logsEnvio":[],"correosElectronicos":[]}