{"numeroHistoriaClinica":"357265","apellidosPaciente":"DIAZ AVALOS","nombresPaciente":"PABLO RAUL","sc":"0022118254","fechaExamen":"2024-04-09","horaExamen":"19:00:01","origen":"Consulta Externa","servicio":"IMAGEN","medico":"KARINA VALERIA CORONEL BRASSEA","motivo":"CAJA 5","ultimaValidacion":"","ultimoFiltrado":"","fechaEnvio":"","tipoValidacion":0,"validacionClinica":0,"validacionMicro":0,"procesoValidacion":0,"statusFiltro":0,"statusEnvio":0,"_PDF":"","_PCR":0,"_AC":0,"numEnvios":0,"enviosParciales":0,"validacionesParciales":[],"orderTests":[],"dataClinica":[],"dataMicro":[],"reglasFiltrosEnvio":[],"reglasFiltrosNoEnvio":[],"formatoQR":[],"logsEnvio":[],"correosElectronicos":[]}