{"numeroHistoriaClinica":"995920","apellidosPaciente":"ARMIJOS PILATAXI","nombresPaciente":"JUANA GEOCONDA","sc":"0022105615","fechaExamen":"2024-02-07","horaExamen":"20:46:17","origen":"Urgencias","servicio":"GINECOLOGIA Y OBSTETRICIA","medico":"DEL POZO OROZCO MARCO ANTONIO","motivo":"METROLAB","ultimaValidacion":"","ultimoFiltrado":"","fechaEnvio":"","tipoValidacion":0,"validacionClinica":0,"validacionMicro":0,"procesoValidacion":0,"statusFiltro":0,"statusEnvio":0,"_PDF":"","_PCR":0,"_AC":0,"numEnvios":0,"enviosParciales":0,"validacionesParciales":[],"orderTests":[],"dataClinica":[],"dataMicro":[],"reglasFiltrosEnvio":[],"reglasFiltrosNoEnvio":[],"formatoQR":[],"logsEnvio":[],"correosElectronicos":[]}