{"numeroHistoriaClinica":"693433","apellidosPaciente":"MOSCOSO IZQUIERDO","nombresPaciente":"PAUL SEBASTIAN","sc":"0022094378","fechaExamen":"2023-12-12","horaExamen":"09:34:52","origen":"Consulta Externa","servicio":"PEDIATRIA","medico":"MOSCOSO MESIAS PAUL ENRIQUE","motivo":"CAJA 4","ultimaValidacion":"","ultimoFiltrado":"","fechaEnvio":"","tipoValidacion":0,"validacionClinica":0,"validacionMicro":0,"procesoValidacion":0,"statusFiltro":0,"statusEnvio":0,"_PDF":"","_PCR":0,"_AC":0,"numEnvios":0,"enviosParciales":0,"validacionesParciales":[],"orderTests":[],"dataClinica":[],"dataMicro":[],"reglasFiltrosEnvio":[],"reglasFiltrosNoEnvio":[],"formatoQR":[],"logsEnvio":[],"correosElectronicos":[]}