{"numeroHistoriaClinica":"47041501","apellidosPaciente":"FURLAN YANEZ","nombresPaciente":"VIRGINIA LUCIA","sc":"0020506974","fechaExamen":"2024-04-03","horaExamen":"17:15:38","origen":"Consulta Externa","servicio":"LABORATORIO","medico":"MEDICO AUTORIZADO  EXTERNO:","motivo":"PREANALITICA","ultimaValidacion":"","ultimoFiltrado":"","fechaEnvio":"","tipoValidacion":0,"validacionClinica":0,"validacionMicro":0,"procesoValidacion":0,"statusFiltro":0,"statusEnvio":0,"_PDF":"","_PCR":0,"_AC":0,"numEnvios":0,"enviosParciales":0,"validacionesParciales":[],"orderTests":[],"dataClinica":[],"dataMicro":[],"reglasFiltrosEnvio":[],"reglasFiltrosNoEnvio":[],"formatoQR":[],"logsEnvio":[],"correosElectronicos":[]}