{"numeroHistoriaClinica":"475085","apellidosPaciente":"NARANJO CORDOVA","nombresPaciente":"IVAN MAURICIO","sc":"0022099247","fechaExamen":"2024-01-07","horaExamen":"04:00:19","origen":"Urgencias","servicio":"MEDICINA INTERNA","medico":"CASTILLO BELTRAN DANIEL ANTONIO","motivo":"METROLAB","ultimaValidacion":"","ultimoFiltrado":"","fechaEnvio":"","tipoValidacion":0,"validacionClinica":0,"validacionMicro":0,"procesoValidacion":0,"statusFiltro":0,"statusEnvio":0,"_PDF":"","_PCR":0,"_AC":0,"numEnvios":0,"enviosParciales":0,"validacionesParciales":[],"orderTests":[],"dataClinica":[],"dataMicro":[],"reglasFiltrosEnvio":[],"reglasFiltrosNoEnvio":[],"formatoQR":[],"logsEnvio":[],"correosElectronicos":[]}