{"numeroHistoriaClinica":"484298","apellidosPaciente":"ROMERO CARVAJAL","nombresPaciente":"JUAN JOSE","sc":"0022116274","fechaExamen":"2024-03-30","horaExamen":"20:27:29","origen":"Urgencias","servicio":"EMERGENCIA","medico":"ULLAURI SOLORZANO VLADIMIR ERNESTO","motivo":"METROLAB","ultimaValidacion":"","ultimoFiltrado":"","fechaEnvio":"","tipoValidacion":0,"validacionClinica":0,"validacionMicro":0,"procesoValidacion":0,"statusFiltro":0,"statusEnvio":0,"_PDF":"","_PCR":0,"_AC":0,"numEnvios":0,"enviosParciales":0,"validacionesParciales":[],"orderTests":[],"dataClinica":[],"dataMicro":[],"reglasFiltrosEnvio":[],"reglasFiltrosNoEnvio":[],"formatoQR":[],"logsEnvio":[],"correosElectronicos":[]}