{"numeroHistoriaClinica":"76599601","apellidosPaciente":"PRUEBA","nombresPaciente":"UN MES","sc":"0019891005","fechaExamen":"2023-08-21","horaExamen":"13:31:32","origen":"Consulta Externa","servicio":"LABORATORIO","medico":"BROZ ENDERS MICHAEL KAREL","motivo":"URGENCIAS","ultimaValidacion":"2024-05-15 13:54:01","ultimoFiltrado":"2023-08-21 15:36:28","fechaEnvio":"2023-08-21 15:40:02","tipoValidacion":0,"validacionClinica":0,"validacionMicro":0,"procesoValidacion":0,"statusFiltro":1,"statusEnvio":5,"_PDF":"","_PCR":0,"_AC":0,"numEnvios":1,"enviosParciales":1,"validacionesParciales":{"Content":"http:\/\/172.16.2.221:9390\/Reports\/pdf\/preview_1_995856.pdf"},"orderTests":[{"TestID":"3119"},{"TestID":"3120"},{"TestID":"3121"}],"dataClinica":[],"dataMicro":[],"reglasFiltrosEnvio":[{"id":"1","nombreFiltro":"ENVIAR SOLO CONSULTA EXTERNA","eNe":"1","tipoValidacion":"1","strValidacion":"1","xServicio":null,"xOrigen":"Consulta Externa","xMotivo":null,"xMedico":null,"xIdPrueba":null,"xQR":null,"envio":"{\"dirrecciones\": \"1\"}","statusFiltro":"1","timestampCreate":null,"userCreate":null,"statusEnvio":0}],"reglasFiltrosNoEnvio":[],"formatoQR":[],"logsEnvio":[{"correosPaciente":[{"To":"prueba1@gmail.com","SubmittedAt":"2023-08-21T20:40:02.7472633Z","MessageID":"0645ddec-47d2-484d-aeb1-4ae2c9db7b9a","ErrorCode":0,"Message":"OK"}]},{"timestampLog":"2023-08-21 15:40:02","log":"Proceso de env\u00edo Exitoso"},{"timestampLog":"2023-08-21 15:40:02","log":"Reproceso por Revalidaci\u00f3n de resultado."}],"correosElectronicos":[{"dirrecciones":"prueba1@gmail.com"}],"logValidacion":{"PreviewResult":"http:\/\/172.16.2.221:9390\/Reports\/pdf\/preview_1_995856.pdf"},"corteEnvio":2}