{"numeroHistoriaClinica":"299494","apellidosPaciente":"ROBALINO HIDALGO","nombresPaciente":"TANGEE VIOLETA","sc":"0022057488","fechaExamen":"2023-06-13","horaExamen":"07:47:53","origen":"Consulta Externa","servicio":"MEDICINA INTERNA","medico":"GARCES NUNEZ RICARDO MAURICIO","motivo":"CAJA 3","ultimaValidacion":"2024-05-15 15:42:02","ultimoFiltrado":"2023-06-13 12:36:28","fechaEnvio":"2023-06-13 14:02:08","tipoValidacion":0,"validacionClinica":0,"validacionMicro":0,"procesoValidacion":0,"statusFiltro":1,"statusEnvio":5,"_PDF":"","_PCR":0,"_AC":0,"numEnvios":1,"enviosParciales":1,"validacionesParciales":{"Content":"http:\/\/172.16.2.221:9390\/Reports\/pdf\/preview_1_977685.pdf"},"orderTests":[{"TestID":"1001"},{"TestID":"1003"},{"TestID":"1005"},{"TestID":"1007"},{"TestID":"1009"},{"TestID":"1011"},{"TestID":"1013"},{"TestID":"1015"},{"TestID":"1017"},{"TestID":"1019"},{"TestID":"1021"},{"TestID":"1023"},{"TestID":"1025"},{"TestID":"1027"},{"TestID":"1029"},{"TestID":"1031"},{"TestID":"1032"},{"TestID":"1033"},{"TestID":"1034"},{"TestID":"1035"},{"TestID":"1036"},{"TestID":"1037"},{"TestID":"1038"},{"TestID":"1039"},{"TestID":"1041"},{"TestID":"1043"},{"TestID":"1044"},{"TestID":"1076"},{"TestID":"1775"},{"TestID":"2033"},{"TestID":"2039"},{"TestID":"2042"},{"TestID":"2045"},{"TestID":"2048"},{"TestID":"2301"},{"TestID":"2371"},{"TestID":"2372"},{"TestID":"2701"},{"TestID":"2704"},{"TestID":"2707"},{"TestID":"2710"},{"TestID":"2713"},{"TestID":"3042"},{"TestID":"4001"},{"TestID":"4004"},{"TestID":"4007"},{"TestID":"4008"},{"TestID":"4011"},{"TestID":"4016"},{"TestID":"4019"},{"TestID":"4022"},{"TestID":"4025"},{"TestID":"4028"},{"TestID":"4031"},{"TestID":"4033"},{"TestID":"4034"},{"TestID":"4038"},{"TestID":"4041"},{"TestID":"4044"},{"TestID":"4045"},{"TestID":"4047"},{"TestID":"4052"},{"TestID":"4053"},{"TestID":"4055"},{"TestID":"4058"},{"TestID":"4061"},{"TestID":"4062"},{"TestID":"4063"},{"TestID":"4064"},{"TestID":"4065"}],"dataClinica":[],"dataMicro":[],"reglasFiltrosEnvio":[{"id":"1","nombreFiltro":"ENVIAR SOLO CONSULTA EXTERNA","eNe":"1","tipoValidacion":"1","strValidacion":"1","xServicio":null,"xOrigen":"Consulta Externa","xMotivo":null,"xMedico":null,"xIdPrueba":null,"xQR":null,"envio":"{\"dirrecciones\": \"1\"}","statusFiltro":"1","timestampCreate":null,"userCreate":null,"statusEnvio":0}],"reglasFiltrosNoEnvio":[],"formatoQR":[],"logsEnvio":[{"correosPaciente":[{"To":"martinfranciscochavez@gmail.com","SubmittedAt":"2023-06-13T19:02:08.8330323Z","MessageID":"d44092d7-8fde-471c-b62e-6956c9d90a12","ErrorCode":0,"Message":"OK"}]},{"timestampLog":"2023-06-13 14:02:08","log":"Proceso de env\u00edo Exitoso"},{"timestampLog":"2023-06-13 14:02:08","log":"Reproceso por Revalidaci\u00f3n de resultado."}],"correosElectronicos":[{"dirrecciones":"marialexnr@hotmail.com"}],"logValidacion":{"PreviewResult":"http:\/\/172.16.2.221:9390\/Reports\/pdf\/preview_1_977685.pdf"},"corteEnvio":2}