{"numeroHistoriaClinica":"76599601","apellidosPaciente":"PRUEBA","nombresPaciente":"UN MES","sc":"0019761780","fechaExamen":"2023-07-03","horaExamen":"08:28:25","origen":"Consulta Externa","servicio":"LABORATORIO","medico":"ZAMBRANO VAREA MARCO E ARMANDO","motivo":"URGENCIAS","ultimaValidacion":"2024-05-15 18:30:02","ultimoFiltrado":"2023-07-03 12:09:26","fechaEnvio":"2023-07-03 14:00:07","tipoValidacion":0,"validacionClinica":0,"validacionMicro":0,"procesoValidacion":1,"statusFiltro":1,"statusEnvio":5,"_PDF":"","_PCR":0,"_AC":0,"numEnvios":1,"enviosParciales":1,"validacionesParciales":{"Content":"http:\/\/172.16.2.221:9390\/Reports\/pdf\/preview_1_983034.pdf"},"orderTests":[{"TestID":"2339"},{"TestID":"7165"},{"TestID":"7300"},{"TestID":"7310"},{"TestID":"7315"},{"TestID":"7771"},{"TestID":"7772"},{"TestID":"7773"},{"TestID":"7774"},{"TestID":"7775"},{"TestID":"7776"},{"TestID":"7777"},{"TestID":"7778"},{"TestID":"7779"},{"TestID":"7780"},{"TestID":"7781"},{"TestID":"7782"},{"TestID":"7783"},{"TestID":"7784"},{"TestID":"7795"},{"TestID":"7999"},{"TestID":"8000"},{"TestID":"8002"},{"TestID":"8004"}],"dataClinica":[],"dataMicro":[{"TestID":"7300","TestStatus":"0","TestName":"Gram.","ultimaValidacion":"2023-07-03 15:30:16"},{"TestID":"7310","TestStatus":"0","TestName":"Ziehl.","ultimaValidacion":"2023-07-03 15:30:16"},{"TestID":"7315","TestStatus":"0","TestName":"Tinta China.","ultimaValidacion":"2023-07-03 15:30:16"},{"TestID":"7165","TestStatus":"0","TestName":"Cultivo de L\u00edquido Cefalo Raqu\u00eddeo","ultimaValidacion":"2023-07-03 15:30:16"}],"reglasFiltrosEnvio":[{"id":"1","nombreFiltro":"ENVIAR SOLO CONSULTA EXTERNA","eNe":"1","tipoValidacion":"1","strValidacion":"1","xServicio":null,"xOrigen":"Consulta Externa","xMotivo":null,"xMedico":null,"xIdPrueba":null,"xQR":null,"envio":"{\"dirrecciones\": \"1\"}","statusFiltro":"1","timestampCreate":null,"userCreate":null,"statusEnvio":0}],"reglasFiltrosNoEnvio":[],"formatoQR":[],"logsEnvio":[{"correosPaciente":[{"To":"martinfranciscochavez@gmail.com","SubmittedAt":"2023-07-03T19:00:06.9924396Z","MessageID":"9d1c36ee-b2c7-43d3-83ad-e6bb44a8353a","ErrorCode":0,"Message":"OK"}]},{"timestampLog":"2023-07-03 14:00:07","log":"Proceso de env\u00edo Exitoso"},{"timestampLog":"2023-07-03 14:00:07","log":"Reproceso por Revalidaci\u00f3n de resultado."}],"correosElectronicos":[{"dirrecciones":"prueba1@gmail.com"}],"logValidacion":{"PreviewResult":"http:\/\/172.16.2.221:9390\/Reports\/pdf\/preview_1_983034.pdf"},"corteEnvio":2}