{"numeroHistoriaClinica":"227447","apellidosPaciente":"SUAREZ BASTIDAS","nombresPaciente":"LUCIA PATRICIA","sc":"0022125762","fechaExamen":"2024-05-15","horaExamen":"10:20:02","origen":"Consulta Externa","servicio":"HEMATOLOGIA","medico":"ROJAS NOBOA JOHANNA CAROLINA","motivo":"CAJA 2","ultimaValidacion":"2024-05-15 13:36:01","ultimoFiltrado":"2024-05-15 13:12:19","fechaEnvio":"","tipoValidacion":1,"validacionClinica":1,"validacionMicro":0,"procesoValidacion":1,"statusFiltro":1,"statusEnvio":0,"_PDF":"","_PCR":0,"_AC":11,"numEnvios":0,"enviosParciales":1,"validacionesParciales":{"Content":"http:\/\/172.16.2.221:9390\/Reports\/pdf\/preview_1_1063522.pdf"},"orderTests":[{"TestID":"1250"},{"TestID":"1251"},{"TestID":"1259"},{"TestID":"1261"}],"dataClinica":[{"TestID":"1250","TestStatus":"4","TestName":"Tp","ultimaValidacion":"2024-05-15 13:36:03"},{"TestID":"1251","TestStatus":"4","TestName":"Inr","ultimaValidacion":"2024-05-15 13:36:03"},{"TestID":"1259","TestStatus":"5","TestName":"Dosis","ultimaValidacion":"2024-05-15 13:36:03"},{"TestID":"1261","TestStatus":"5","TestName":"Pr\u00f3ximo Control","ultimaValidacion":"2024-05-15 13:36:03"}],"dataMicro":[],"reglasFiltrosEnvio":[{"id":"1","nombreFiltro":"ENVIAR SOLO CONSULTA EXTERNA","eNe":"1","tipoValidacion":"1","strValidacion":"1","xServicio":null,"xOrigen":"Consulta Externa","xMotivo":null,"xMedico":null,"xIdPrueba":null,"xQR":null,"envio":"{\"dirrecciones\": \"1\"}","statusFiltro":"1","timestampCreate":null,"userCreate":null,"statusEnvio":0}],"reglasFiltrosNoEnvio":[],"formatoQR":[],"logsEnvio":[{"timestampLog":"2024-05-15 13:40:38","log":["OpenSSL SSL_connect: SSL_ERROR_SYSCALL in connection to api.trx.icommarketing.com:443 "]},{"timestampLog":"2024-05-15 13:40:38","log":"Proceso de env\u00edo con Error ning\u00fan correo electr\u00f3nico respondio afirmativamente."},{"timestampLog":"2024-05-15 13:40:38","log":"Error en proceso de env\u00edo"},{"timestampLog":"2024-05-15 15:32:06","log":["SSL: certificate subject name 'testexp' does not match target host name 'api.trx.icommarketing.com'"]},{"timestampLog":"2024-05-15 15:32:06","log":"Proceso de env\u00edo con Error ning\u00fan correo electr\u00f3nico respondio afirmativamente."},{"timestampLog":"2024-05-15 15:32:06","log":"Error en proceso de env\u00edo"}],"correosElectronicos":[{"dirrecciones":"alfredogallegosch@outlook.com"}],"logValidacion":{"PreviewResult":"http:\/\/172.16.2.221:9390\/Reports\/pdf\/preview_1_1063522.pdf"},"corteEnvio":2}